worktimething/__init__.py
worktimething/__main__.py
worktimething/core.py
worktimething/testing.py
worktimething-0.1.7.dist-info/WHEEL
worktimething-0.1.7.dist-info/METADATA
worktimething-0.1.7.dist-info/RECORD
