Metadata-Version: 2.1
Name: worktimething
Version: 0.1.7
Summary: A simple cli tool to record time spent on tasks.
Home-page: https://github.com/theSage21/worktime
Author: arjoonn sharma
Author-email: arjoonn.94@gmail.com
Requires-Python: >=3.6,<4.0
Classifier: Programming Language :: Python :: 3
Classifier: Programming Language :: Python :: 3.6
Classifier: Programming Language :: Python :: 3.7
Classifier: Programming Language :: Python :: 3.8
Requires-Dist: click (>=7.1.2,<8.0.0)
Project-URL: Repository, https://github.com/theSage21/worktime
